<annotation>
    <folder>PCB</folder>
    <filename>rotation_270_light_08_open_circuit_01_4_600</filename>
    <source>
        <database>My Database</database>
        <annotation>PCB</annotation>
        <image>flickr</image>
        <flickrid>NULL</flickrid>
    </source>
    <owner>
        <flickrid>NULL</flickrid>
        <name>idaneel</name>
    </owner>
    <size>
        <width>601</width>
        <height>601</height>
        <depth>3</depth>
    </size>
    <segmented>0</segmented>
    <object>
        <name>open_circuit</name>
        <pose>Unspecified</pose>
        <truncated>0</truncated>
        <difficult>0</difficult>
        <bndbox>
            <xmin>424</xmin>
            <ymin>50</ymin>
            <xmax>448</xmax>
            <ymax>69</ymax>
        </bndbox>
    </object>
    <object>
        <name>open_circuit</name>
        <pose>Unspecified</pose>
        <truncated>0</truncated>
        <difficult>0</difficult>
        <bndbox>
            <xmin>133</xmin>
            <ymin>36</ymin>
            <xmax>154</xmax>
            <ymax>60</ymax>
        </bndbox>
    </object>
    <object>
        <name>open_circuit</name>
        <pose>Unspecified</pose>
        <truncated>0</truncated>
        <difficult>0</difficult>
        <bndbox>
            <xmin>519</xmin>
            <ymin>177</ymin>
            <xmax>537</xmax>
            <ymax>197</ymax>
        </bndbox>
    </object>
</annotation>